pco_image/__init__.py
pco_image/config.py
pco_image/image.py
pco_image-0.2.0.dist-info/LICENSE
pco_image-0.2.0.dist-info/METADATA
pco_image-0.2.0.dist-info/WHEEL
pco_image-0.2.0.dist-info/top_level.txt
pco_image-0.2.0.dist-info/RECORD
