Metadata-Version: 2.1
Name: pco-image
Version: 0.2.0
Summary: Tool to read and extract meta data from pco images
Home-page: https://github.com/matthiasprobst/pco_image
Author: Matthias Probst
Author-email: matth.probst@gmail.com
Classifier: Programming Language :: Python :: 3
Classifier: License :: OSI Approved :: MIT License
Classifier: Programming Language :: Python :: 3.7
Classifier: Programming Language :: Python :: 3.8
Classifier: Programming Language :: Python :: 3.9
Classifier: Programming Language :: Python :: 3.10
Classifier: License :: OSI Approved :: GNU General Public License v3 (GPLv3)
Classifier: Operating System :: OS Independent
Classifier: Development Status :: 4 - Beta
Requires-Python: >=3.7
License-File: LICENSE
Requires-Dist: pco-tools
Requires-Dist: numpy
Provides-Extra: test
Requires-Dist: pytest ; extra == 'test'
